{
    "Name": "Nasuni",
    "Author": "Nasuni - support@nasuni.com",
    "Logo": "<img src=\"https://raw.githubusercontent.com/Azure/Azure-Sentinel/master/Solutions/Nasuni/Data%20Connectors/Logo/Nasuni.svg\" width=\"75px\" height=\"75px\">",
    "Description": "The [Nasuni](https://www.nasuni.com) solution for Microsoft Sentinel allows you to analyze Nasuni audit events and Notifications collected via Syslog. It includes analytics rules to automatically generate Incidents when a ransomware attack is detected and perform appropriate entity mapping.",
    "Analytic Rules": [
      "/Nasuni/Analytic Rules/RansomwareClientBlocked.yaml",
      "/Nasuni/Analytic Rules/RansomwareAttackDetected.yaml"
    ],
    "Hunting Queries": [
      "/Nasuni/Hunting Queries/FileDeleteEvents.yaml"
    ],
    "Data Connectors": [
      "/Nasuni/Data Connectors/Nasuni Data Connector.json"
    ],
    "BasePath": "C:\\GitHub\\Azure-Sentinel\\Solutions",
    "Version": "3.0.0",
    "Metadata": "SolutionMetadata.json",
    "TemplateSpec": true,
    "Is1PConnector": false
  }