{
    "$schema": "https://schema.management.azure.com/schemas/2019-04-01/deploymentTemplate.json#",
    "contentVersion": "1.0.0.0",
    "metadata": {
        "title": "Retrieve Alert from Microsoft Sentinel and Trigger a Blink Workflow via Webhook",
        "description": "Send a webhook request to a Blink workflow trigger whenever a new alert is created in Microsoft Sentinel",
        "prerequisites": [
            "Set up a new Microsoft XDR webhook in Blink before deploying this playbook",
            "Copy the Webhook Full URL from the configured Microsoft XDR webhook"
        ],
        "postDeployment": [
            "Once deployed, go to your Microsoft Sentinel workspace > Configuration > Automation, click 'Create', and choose 'Automation rule' to set up a new rule that will send a notification to Blink when a new Sentinel alert is triggered.",
            "Assign a descriptive name to the automation rule.",
            "In the Trigger section, choose 'When alert is created'.",
            "In the Actions section, select 'Run playbook'.",
            "From the playbook list, pick 'Sentinel-Alert-Handler' and click 'Apply'."
        ],
        "lastUpdateTime": "2025-05-04T00:00:00.000Z",
        "author": {
            "name": "Blink"
        },
        "releaseNotes": [
            {
                "version": "1.0.0",
                "title": "Sentinel-Alert-Handler",
                "notes": [ "Initial version" ]
            }
        ],
        "support": {
            "tier": "Partner"
        }
    },
    "parameters": {
        "PlaybookName": {
            "defaultValue": "Sentinel-Alert-Handler",
            "type": "string"
        }
    },
    "variables": {
        "AzureSentinelConnectionName": "[concat('azuresentinel-', parameters('PlaybookName'))]"
    },
    "resources": [
        {
            "type": "Microsoft.Web/connections",
            "apiVersion": "2016-06-01",
            "name": "[variables('AzureSentinelConnectionName')]",
            "location": "[resourceGroup().location]",
            "kind": "V1",
            "properties": {
                "displayName": "[variables('AzureSentinelConnectionName')]",
                "customParameterValues": {},
                "parameterValueType": "Alternative",
                "api": {
                    "id": "[concat('/subscriptions/', subscription().subscriptionId, '/providers/Microsoft.Web/locations/', resourceGroup().location, '/managedApis/azuresentinel')]"
                }
            }
        },
        {
            
            "type": "Microsoft.Logic/workflows",
            "apiVersion": "2017-07-01",
            "name": "[parameters('PlaybookName')]",
            "location": "[resourceGroup().location]",
            "identity": {
                "type": "SystemAssigned"
            },
            "dependsOn": [
                "[resourceId('Microsoft.Web/connections', variables('AzureSentinelConnectionName'))]"
            ],
            "properties": {
                "state": "Enabled",
                "definition": {
                    "$schema": "https://schema.management.azure.com/providers/Microsoft.Logic/schemas/2016-06-01/workflowdefinition.json#",
                    "contentVersion": "1.0.0.0",
                    "parameters": {
                        "Blink-Webhook-Full-URL": {
                            "defaultValue": "https://{tenant_subdomain}.blinkops.com/webhooks/{webhook_id}?apikey={api_key}",
                            "type": "String"
                        },
                        "PlaybookName": {
                            "defaultValue": "Sentinel-Alert-Handler",
                            "type": "string"
                        },
                        "$connections": {
                            "defaultValue": {},
                            "type": "Object"
                        }
                    },
                    "triggers": {
                        "Microsoft_Sentinel_alert": {
                            "type": "ApiConnectionWebhook",
                            "inputs": {
                                "host": {
                                    "connection": {
                                        "name": "@parameters('$connections')['azuresentinel']['connectionId']"
                                    }
                                },
                                "body": {
                                    "callback_url": "@listCallbackUrl()"
                                },
                                "path": "/subscribe"
                            }
                        }
                    },
                    "actions": {
                        "Trigger_Blink_Workflow": {
                            "runAfter": {},
                            "limit": {
                                "timeout": "PT30S"
                            },
                            "type": "Http",
                            "inputs": {
                              "body": "@triggerBody()?['object']",
                              "method": "POST",
                              "uri": "@parameters('Blink-Webhook-Full-URL')"
                            },
                            "operationOptions": "DisableAsyncPattern"
                        },
                        "Terminate_Success": {
                            "runAfter": {
                                "Trigger_Blink_Workflow": [
                                "Succeeded"
                                ]
                            },
                            "type": "Terminate",
                            "inputs": {
                                "runStatus": "Succeeded"
                            }
                        }
                    },
                    "outputs": {}
                },
                "parameters": {
                    "$connections": {
                        "value": {
                            "azuresentinel": {
                                "id": "[concat('/subscriptions/', subscription().subscriptionId, '/providers/Microsoft.Web/locations/', resourceGroup().location, '/managedApis/azuresentinel')]",
                                "connectionId": "[resourceId('Microsoft.Web/connections', variables('AzureSentinelConnectionName'))]",
                                "connectionName": "[variables('AzureSentinelConnectionName')]",
                                "connectionProperties": {
                                    "authentication": {
                                        "type": "ManagedServiceIdentity"
                                    }
                                }
                            }
                        }
                    }
                }
            }
        }
    ]
}